django_yaa_settings-0.1.0.dist-info/METADATA
django_yaa_settings-0.1.0.dist-info/RECORD
django_yaa_settings-0.1.0.dist-info/WHEEL
django_yaa_settings-0.1.0.dist-info/top_level.txt
django_yaa_settings-0.1.0.dist-info/zip-safe
yaa_settings/__init__.py
yaa_settings/app_settings.py
