Metadata-Version: 2.1
Name: django-yaa-settings
Version: 0.1.0
Summary: Yet Another App Settings for Django
Home-page: http://radiac.net/projects/django-yaa-settings/
Author: Richard Terry
Author-email: code@radiac.net
License: BSD
Platform: UNKNOWN
Classifier: Development Status :: 5 - Production/Stable
Classifier: Environment :: Web Environment
Classifier: Intended Audience :: Developers
Classifier: License :: OSI Approved :: BSD License
Classifier: Operating System :: OS Independent
Classifier: Programming Language :: Python :: 2
Classifier: Programming Language :: Python :: 2.7
Classifier: Programming Language :: Python :: 3
Classifier: Programming Language :: Python :: 3.4
Classifier: Programming Language :: Python :: 3.5
Classifier: Programming Language :: Python :: 3.6
Classifier: Framework :: Django
Classifier: Framework :: Django :: 1.8
Classifier: Framework :: Django :: 1.11
Classifier: Framework :: Django :: 2.0
Provides-Extra: dev
Provides-Extra: dev
Requires-Dist: tox; extra == 'dev'
